pygram/__init__.py
pygram/errors.py
pygram/helper.py
pygram/pygram.py
pygram-0.0.13b0.dist-info/LICENSE
pygram-0.0.13b0.dist-info/METADATA
pygram-0.0.13b0.dist-info/WHEEL
pygram-0.0.13b0.dist-info/top_level.txt
pygram-0.0.13b0.dist-info/RECORD
